zeroconf_monkey.py
zeroconf_monkey-1.0.1.dist-info/LICENSE
zeroconf_monkey-1.0.1.dist-info/METADATA
zeroconf_monkey-1.0.1.dist-info/WHEEL
zeroconf_monkey-1.0.1.dist-info/top_level.txt
zeroconf_monkey-1.0.1.dist-info/RECORD
