Metadata-Version: 2.1
Name: zeroconf-monkey
Version: 1.0.1
Summary: A thin wrapper on top of Zeroconf to override validation
Home-page: https://github.com/bbc/zeroconf_monkey
Author: Peter Brightwell
Author-email: peter.brightwell@bbc.co.uk
License: LGPL
Platform: UNKNOWN
Requires-Dist: zeroconf (<=0.28.5,>=0.25.0)
